{
  "id": "hu-law-2001-77-00-00",
  "type": "statute",
  "title": "2001. évi LXXVII. törvény a szerzői jogról szóló 1999. évi LXXVI. törvény módosításáról",
  "status": "repealed",
  "in_force_date": "2002-01-01",
  "url": "https://njt.hu/jogszabaly/2001-77-00-00",
  "description": "a szerzői jogról szóló 1999. évi LXXVI. törvény módosításáról",
  "provisions": [
    {
      "provision_ref": "s112",
      "section": "1–12",
      "title": "1–12. §",
      "content": "1–12. §"
    },
    {
      "provision_ref": "s13",
      "section": "13",
      "title": "13. §",
      "content": "13. § (1) E törvény 2002. január 1-jén lép hatályba; rendelkezéseit a hatálybalépését követően megkötött felhasználási szerződésekre kell alkalmazni. (2) E törvénynek az adatbázis-előállítók védelmére vonatkozó rendelkezéseit alkalmazni kell arra az adatbázisra is, amelyet e törvény hatálybalépése előtt, de 1982. december 31-ét követően készítettek el, feltéve, hogy a hatálybalépés napján az adatbázis megfelel az Szjt. – e törvény 8. §-ának (2) bekezdésével megállapított – XI/A. fejezetében szabályozott védelem feltételeinek. (3) A (2) bekezdésben szabályozott adatbázis előállítójának jogai e törvény hatálybalépésétől kezdődően részesülnek védelemben, de csak 1998. január 1-jétől számított tizenöt évig. (4) A (2) bekezdésben szabályozott adatbázisnak a törvény hatálybalépése előtt megkezdett felhasználása – kimásolása, illetve újrahasznosítása – a hatálybalépést követő egy évig folytatható, de csak a hatálybalépéskor meglévő mértékben. A gazdasági tevékenység körében folytatott ilyen felhasználás jogát csak a jogosult gazdálkodó szervezettel vagy annak – a felhasználást folytató – szervezeti egységével együtt lehet átruházni. (5) A (4) bekezdésben foglalt rendelkezéseket megfelelően alkalmazni kell akkor is, ha a felhasználásra e törvény kihirdetésének napjáig komoly előkészületeket tettek, azzal, hogy ebben az esetben a felhasználást az előkészületnek az e törvény kihirdetésekor meglévő mértékéig lehet megkezdeni és folytatni. (6) Az adatbázis előállítójával e törvény hatálybalépését megelőzően kötött – a (2) bekezdésben szabályozott adatbázis felhasználására vonatkozó – szerződés alapján végzett cselekményekre a szerződés megkötésekor hatályos rendelkezéseket kell alkalmazni e törvény hatálybalépését követően is. (7) Az Szjt. 84. §-ának e törvény 7. §-ával megállapított (2) bekezdését nem lehet alkalmazni olyan hangfelvételekre, amelyeknek a korábban hatályos rendelkezések szerint számított védelmi ideje már lejárt. E rendelkezés nem érinti az Szjt. 108. §-ának alkalmazását."
    }
  ],
  "definitions": []
}
