{
  "id": "hu-law-2011-197-00-00",
  "type": "statute",
  "title": "2011. évi CXCVII. törvény a csődeljárásról és a felszámolási eljárásról szóló 1991. évi XLIX. törvény, a gazdasági társaságokról szóló 2006. évi IV. törvény, a cégnyilvánosságról, a bírósági cégeljárásról és a végelszámolásról szóló 2006. évi V. törvény, továbbá az ezekkel összefüggő egyes törvények módosításáról",
  "status": "repealed",
  "in_force_date": "2012-01-01",
  "url": "https://njt.hu/jogszabaly/2011-197-00-00",
  "description": "a csődeljárásról és a felszámolási eljárásról szóló 1991. évi XLIX. törvény, a gazdasági társaságokról szóló 2006. évi IV. törvény, a cégnyilvánosságról, a bírósági cégeljárásról és a végelszámolásról szóló 2006. évi V. törvény, továbbá az ezekkel összefüggő egyes törvények módosításáról",
  "provisions": [
    {
      "provision_ref": "s1",
      "section": "1",
      "title": "1. §",
      "content": "1. §"
    },
    {
      "provision_ref": "s2",
      "section": "2",
      "title": "2. §",
      "content": "2. §"
    },
    {
      "provision_ref": "s3",
      "section": "3",
      "title": "3. §",
      "content": "3. §"
    },
    {
      "provision_ref": "s4",
      "section": "4",
      "title": "4. §",
      "content": "4. §"
    },
    {
      "provision_ref": "s5",
      "section": "5",
      "title": "5. §",
      "content": "5. §"
    },
    {
      "provision_ref": "s6",
      "section": "6",
      "title": "6. §",
      "content": "6. § (1) (2) (3) (4)"
    },
    {
      "provision_ref": "s7",
      "section": "7",
      "title": "7. §",
      "content": "7. §"
    },
    {
      "provision_ref": "s8",
      "section": "8",
      "title": "8. §",
      "content": "8. §"
    },
    {
      "provision_ref": "s9",
      "section": "9",
      "title": "9. §",
      "content": "9. §"
    },
    {
      "provision_ref": "s10",
      "section": "10",
      "title": "10. §",
      "content": "10. §"
    },
    {
      "provision_ref": "s11",
      "section": "11",
      "title": "11. §",
      "content": "11. §"
    },
    {
      "provision_ref": "s12",
      "section": "12",
      "title": "12. §",
      "content": "12. §"
    },
    {
      "provision_ref": "s13",
      "section": "13",
      "title": "13. §",
      "content": "13. §"
    },
    {
      "provision_ref": "s14",
      "section": "14",
      "title": "14. §",
      "content": "14. §"
    },
    {
      "provision_ref": "s15",
      "section": "15",
      "title": "15. §",
      "content": "15. §"
    },
    {
      "provision_ref": "s16",
      "section": "16",
      "title": "16. §",
      "content": "16. §"
    },
    {
      "provision_ref": "s17",
      "section": "17",
      "title": "17. §",
      "content": "17. §"
    },
    {
      "provision_ref": "s18",
      "section": "18",
      "title": "18. §",
      "content": "18. §"
    },
    {
      "provision_ref": "s19",
      "section": "19",
      "title": "19. §",
      "content": "19. §"
    },
    {
      "provision_ref": "s20",
      "section": "20",
      "title": "20. §",
      "content": "20. §"
    },
    {
      "provision_ref": "s21",
      "section": "21",
      "title": "21. §",
      "content": "21. §"
    },
    {
      "provision_ref": "s22",
      "section": "22",
      "title": "22. §",
      "content": "22. §"
    },
    {
      "provision_ref": "s23",
      "section": "23",
      "title": "23. §",
      "content": "23. §"
    },
    {
      "provision_ref": "s24",
      "section": "24",
      "title": "24. §",
      "content": "24. §"
    },
    {
      "provision_ref": "s25",
      "section": "25",
      "title": "25. §",
      "content": "25. §"
    },
    {
      "provision_ref": "s26",
      "section": "26",
      "title": "26. §",
      "content": "26. §"
    },
    {
      "provision_ref": "s27",
      "section": "27",
      "title": "27. §",
      "content": "27. §"
    },
    {
      "provision_ref": "s28",
      "section": "28",
      "title": "28. §",
      "content": "28. §"
    },
    {
      "provision_ref": "s29",
      "section": "29",
      "title": "29. §",
      "content": "29. §"
    },
    {
      "provision_ref": "s30",
      "section": "30",
      "title": "30. §",
      "content": "30. §"
    },
    {
      "provision_ref": "s31",
      "section": "31",
      "title": "31. §",
      "content": "31. §"
    },
    {
      "provision_ref": "s32",
      "section": "32",
      "title": "32. §",
      "content": "32. §"
    },
    {
      "provision_ref": "s3360",
      "section": "33–60",
      "title": "33–60. §",
      "content": "33–60. §"
    },
    {
      "provision_ref": "s61",
      "section": "61",
      "title": "61. §",
      "content": "61. §"
    },
    {
      "provision_ref": "s62",
      "section": "62",
      "title": "62. §",
      "content": "62. §"
    },
    {
      "provision_ref": "s63",
      "section": "63",
      "title": "63. §",
      "content": "63. §"
    },
    {
      "provision_ref": "s64",
      "section": "64",
      "title": "64. §",
      "content": "64. §"
    },
    {
      "provision_ref": "s65",
      "section": "65",
      "title": "65. §",
      "content": "65. §"
    },
    {
      "provision_ref": "s66",
      "section": "66",
      "title": "66. §",
      "content": "66. §"
    },
    {
      "provision_ref": "s67",
      "section": "67",
      "title": "67. §",
      "content": "67. § (1) (2)"
    },
    {
      "provision_ref": "s68",
      "section": "68",
      "title": "68. §",
      "content": "68. §"
    },
    {
      "provision_ref": "s69",
      "section": "69",
      "title": "69. §",
      "content": "69. § A Cstv. 1. 2. 3. 4. 5. 6. 7. 8. 9. 10. 11. 12. 13. 14. 15. 16. 17. 18. 19. 20. 21. 22. 23. 24. 25. 26. 27. 28. 29. 30. 31. 32. 33. 34. 35. 36. 37. 38. 39. 40. 41. 42. 43. 44. 45. 46. 47."
    },
    {
      "provision_ref": "s70",
      "section": "70",
      "title": "70. §",
      "content": "70. §"
    },
    {
      "provision_ref": "s71",
      "section": "71",
      "title": "71. §",
      "content": "71. §"
    },
    {
      "provision_ref": "s72",
      "section": "72",
      "title": "72. §",
      "content": "72. §"
    },
    {
      "provision_ref": "s73",
      "section": "73",
      "title": "73. §",
      "content": "73. §"
    },
    {
      "provision_ref": "s109",
      "section": "109",
      "title": "109. §",
      "content": "109. § (1) A Ctv. 24. § (1) bekezdés e) pontja helyébe a következő rendelkezés lép: (A cégjegyzék valamennyi cég esetében tartalmazza) „e) a cég főtevékenységét, valamint további tevékenységi köreit, azok mindenkor hatályos TEÁOR nómenklatúra szerinti megjelölésével,” (2) (3) (4) A Ctv. 24. §-a a következő (4b) bekezdéssel egészül ki: „(4b) A cégbíróság az adóhatóság elektronikus értesítése alapján, hivatalból jegyzi be a cég főtevékenységének és további tevékenységi köreinek változásait, a mindenkor hatályos TEÁOR nómenklatúra szerinti megjelöléssel. Az adat bejegyzése és közzététele automatikusan történik meg.” 110 – 112. §"
    },
    {
      "provision_ref": "s113",
      "section": "113",
      "title": "113. §",
      "content": "113. § (1) (2)"
    },
    {
      "provision_ref": "s114",
      "section": "114",
      "title": "114. §",
      "content": "114. §"
    },
    {
      "provision_ref": "s115",
      "section": "115",
      "title": "115. §",
      "content": "115. §"
    },
    {
      "provision_ref": "s116",
      "section": "116",
      "title": "116. §",
      "content": "116. § (1) (2) 117 – 136. §"
    },
    {
      "provision_ref": "s137",
      "section": "137",
      "title": "137. §",
      "content": "137. §"
    },
    {
      "provision_ref": "s138",
      "section": "138",
      "title": "138. §",
      "content": "138. §"
    },
    {
      "provision_ref": "s139",
      "section": "139",
      "title": "139. §",
      "content": "139. § (1) (2) (3)"
    },
    {
      "provision_ref": "s140",
      "section": "140",
      "title": "140. §",
      "content": "140. §"
    },
    {
      "provision_ref": "s141",
      "section": "141",
      "title": "141. §",
      "content": "141. § Hatályát veszti a Ctv. a) b) 27. § (6) bekezdés b) pontja, c) d) e) f) g) h) i) 131. §-a, j) k)"
    },
    {
      "provision_ref": "s142",
      "section": "142",
      "title": "142. §",
      "content": "142. §"
    },
    {
      "provision_ref": "s143",
      "section": "143",
      "title": "143. §",
      "content": "143. §"
    },
    {
      "provision_ref": "s144",
      "section": "144",
      "title": "144. §",
      "content": "144. §"
    },
    {
      "provision_ref": "s145",
      "section": "145",
      "title": "145. §",
      "content": "145. §"
    },
    {
      "provision_ref": "s146",
      "section": "146",
      "title": "146. §",
      "content": "146. §"
    },
    {
      "provision_ref": "s147",
      "section": "147",
      "title": "147. §",
      "content": "147. §"
    },
    {
      "provision_ref": "s148",
      "section": "148",
      "title": "148. §",
      "content": "148. §"
    },
    {
      "provision_ref": "s149",
      "section": "149",
      "title": "149. §",
      "content": "149. §"
    },
    {
      "provision_ref": "s150",
      "section": "150",
      "title": "150. §",
      "content": "150. §"
    },
    {
      "provision_ref": "s151",
      "section": "151",
      "title": "151. §",
      "content": "151. §"
    },
    {
      "provision_ref": "s152",
      "section": "152",
      "title": "152. §",
      "content": "152. §"
    },
    {
      "provision_ref": "s153",
      "section": "153",
      "title": "153. §",
      "content": "153. §"
    },
    {
      "provision_ref": "s154",
      "section": "154",
      "title": "154. §",
      "content": "154. §"
    },
    {
      "provision_ref": "s155",
      "section": "155",
      "title": "155. §",
      "content": "155. §"
    },
    {
      "provision_ref": "s156",
      "section": "156",
      "title": "156. §",
      "content": "156. §"
    },
    {
      "provision_ref": "s157",
      "section": "157",
      "title": "157. §",
      "content": "157. §"
    },
    {
      "provision_ref": "s158",
      "section": "158",
      "title": "158. §",
      "content": "158. §"
    },
    {
      "provision_ref": "s159",
      "section": "159",
      "title": "159. §",
      "content": "159. §"
    },
    {
      "provision_ref": "s160",
      "section": "160",
      "title": "160. §",
      "content": "160. §"
    },
    {
      "provision_ref": "s162",
      "section": "162",
      "title": "162. §",
      "content": "162. §"
    },
    {
      "provision_ref": "s163",
      "section": "163",
      "title": "163. §",
      "content": "163. §"
    },
    {
      "provision_ref": "s164",
      "section": "164",
      "title": "164. §",
      "content": "164. §"
    },
    {
      "provision_ref": "s165",
      "section": "165",
      "title": "165. §",
      "content": "165. §"
    },
    {
      "provision_ref": "s166",
      "section": "166",
      "title": "166. §",
      "content": "166. §"
    },
    {
      "provision_ref": "s167",
      "section": "167",
      "title": "167. §",
      "content": "167. § (1) Ez a törvény – a (2)–(4) bekezdésben meghatározott kivételekkel – 2012. január 1-jén lép hatályba, és 2013. február 2-án hatályát veszti. (2) A 116. § (1) bekezdés 2012. január 2-án lép hatályba. (3) Az 1–5. §, a 6. § (1)–(2) és (4) bekezdése, a 7–31. §, a 33–60. §, a 66. §, a 67. § (1) bekezdés, a 68. §, a 69. § 1–41. és 46–47. pontja, a 70–108. §, a 109. § (2)–(3) bekezdés, a 110–112. §, a 113. § (1) bekezdés, a 114–115. §, a 116. § (2) bekezdés, a 117–136. §, a 137. §, a 139. § (2)–(3) bekezdés, a 140. §, a 141. § a) pontja, c)–h) pontja, j) pontja, a 159–164. § és az 1–7. melléklet a kihirdetését követő harmadik hónap első napján lép hatályba. (3a) A 6. § (3) bekezdése 2013. január 1-jén lép hatályba."
    }
  ],
  "definitions": []
}
