{
  "id": "hu-law-1990-16-00-00",
  "type": "statute",
  "title": "1990. évi XVI. TÖRVÉNY a Magyar Köztársaság Alkotmányának módosításáról",
  "status": "repealed",
  "in_force_date": "1990-03-12",
  "url": "https://njt.hu/jogszabaly/1990-16-00-00",
  "description": "a Magyar Köztársaság Alkotmányának módosításáról",
  "provisions": [
    {
      "provision_ref": "s17",
      "section": "1–7",
      "title": "1–7. §",
      "content": "1–7. §"
    },
    {
      "provision_ref": "s8",
      "section": "8",
      "title": "8. §",
      "content": "8. § (1) Ez a törvény a kihirdetése napján lép hatályba. (2)–(3) (4) A Magyar Honvédség elnevezést 1990. március 15-től kell alkalmazni. Ahol a jogszabály Magyar Néphadsereget említ, azon Magyar Honvédséget, ahol pedig Magyar Néphadsereg Vezérkarát említ, azon a Magyar Honvédség Vezérkarát kell érteni."
    }
  ],
  "definitions": []
}
