{
  "id": "hu-law-2017-162-00-00",
  "type": "statute",
  "title": "2017. évi CLXII. törvény a sportról szóló 2004. évi I. törvény módosításáról",
  "status": "repealed",
  "in_force_date": "2017-11-24",
  "url": "https://njt.hu/jogszabaly/2017-162-00-00",
  "description": "a sportról szóló 2004. évi I. törvény módosításáról",
  "provisions": [
    {
      "provision_ref": "s1",
      "section": "1",
      "title": "1. §",
      "content": "1. § A sportról szóló 2004. évi I. törvény „Hatályba léptető és átmeneti rendelkezések” alcíme a következő 78/G. §-sal és 78/H. §-sal egészül ki: „78/G. § A 61. § (12) bekezdés c) pontját a 2012. január 1-jét követően megrendezett olimpia, Paralimpia, Sakkolimpia és Siketlimpia tekintetében kell alkalmazni. 78/H. § E törvénynek a sportról szóló 2004. évi I. törvény módosításáról szóló 2017. évi CLXII. törvénnyel megállapított 78/G. §-át a folyamatban lévő ügyekben, az olimpiai járadék iránti kérelem tárgyában hozott közigazgatási határozat bírósági felülvizsgálata iránti perekben és a megismételt eljárásokban is alkalmazni kell.”"
    }
  ],
  "definitions": []
}
