{
  "id": "hu-law-2001-43-00-00",
  "type": "statute",
  "title": "2001. évi XLIII. törvény a Honvédelmi Minisztérium és a Honvéd Vezérkar integrációjával érintett törvények módosításáról",
  "status": "repealed",
  "in_force_date": "2001-07-11",
  "url": "https://njt.hu/jogszabaly/2001-43-00-00",
  "description": "a Honvédelmi Minisztérium és a Honvéd Vezérkar integrációjával érintett törvények módosításáról",
  "provisions": [
    {
      "provision_ref": "s116",
      "chapter": "I. Fejezet",
      "section": "1–16",
      "title": "1–16. §",
      "content": "1–16. §"
    },
    {
      "provision_ref": "s17",
      "chapter": "II. Fejezet",
      "section": "17",
      "title": "17. §",
      "content": "17. §"
    },
    {
      "provision_ref": "s1820",
      "chapter": "II. Fejezet",
      "section": "18–20",
      "title": "18–20. §",
      "content": "18–20. §"
    },
    {
      "provision_ref": "s21",
      "chapter": "III. Fejezet",
      "section": "21",
      "title": "21. §",
      "content": "21. §"
    },
    {
      "provision_ref": "s22",
      "chapter": "IV. Fejezet",
      "section": "22",
      "title": "22. §",
      "content": "22. §"
    },
    {
      "provision_ref": "s23",
      "chapter": "V. Fejezet",
      "section": "23",
      "title": "23. §",
      "content": "23. §"
    },
    {
      "provision_ref": "s24",
      "chapter": "VI. Fejezet",
      "section": "24",
      "title": "24. §",
      "content": "24. §"
    },
    {
      "provision_ref": "s25",
      "chapter": "VII. Fejezet - Záró rendelkezések",
      "section": "25",
      "title": "25. §",
      "content": "25. § (1) Ez a törvény a kihirdetését követő 8. napon lép hatályba. A Honvédelmi Minisztériumnak e törvény szerinti működésre a hatálybalépést követő 6 hónapon belül kell áttérnie. A törvény hatálybalépésével egyidejűleg hatályát veszti – a Hvt. 8. §-a (3) bekezdésének b) pontja és 251. §-a (1) bekezdésének f) pontja, – a Hszt. 85. §-ának (1) és 87. §-ának (1) bekezdésében a,,készültségi'' szövegrész, továbbá 237. § (1) bekezdése b) pontjának első gondolatjeles bekezdése, – a Hkt. 3. §-a (1) bekezdésének c) pontjában, 69. §-a (2) bekezdésének b) pontjában és 72. §-ának (1) bekezdésében a,,készültségi'' kifejezés, – a Hft. 28. §-ának c) pontjában a,,készültségi'' kifejezés. (2) A Hvt. 12. §-ának (2) bekezdésében a,,honvédség parancsnoka vagy a parancsnoksághoz tartozó elöljáró'' szövegrész helyébe a,,Honvéd Vezérkar főnöke vagy a Honvéd Vezérkarhoz tartozó elöljáró'' szövegrész, 23. §-ában, 31. §-ának (2), 33. §-ának (2) és 36. §-ának (1) bekezdésében a,,honvédség parancsnoka'' szövegrész helyébe a,,Honvéd Vezérkar főnöke'' szövegrész, 24. §-ának (1), 31. §-ának (3) és a 114. §-ának (3) bekezdésében a,,honvédség parancsnokának'' szövegrész helyébe a,,Honvéd Vezérkar főnökének'' szövegrész lép. (3) A Hvt. 24. §-ának (1), 83. §-ának (3), 84. §-ának (2), 96. §-ának (5), 99. §-ának (3), 112. §-ának (6), 198. §-ának (5) bekezdésében a,,honvédség vezérkari főnöke'' szövegrész és 103. §-ának (3) bekezdésében a,,vezérkari főnök'' szövegrész helyébe a,,Honvéd Vezérkar főnöke'' szövegrész, 102. §-ának (2) és 111. §-ának (1) bekezdésében a,,honvédség vezérkari főnökéhez'' szövegrész helyébe a,,Honvéd Vezérkar főnökéhez'' szövegrész, 103. §-ának (2) és 129. §-ának (2) bekezdésében a,,honvédség vezérkari főnökétől'' szövegrész helyébe a,,Honvéd Vezérkar főnökétől'' szövegrész lép. (4) A Hvt. 5. §-ának (2) bekezdésében a,,magasabb harckészültségbe helyezésének'' szövegrész helyébe a,,készenléte fokozásának'' szövegrész, 8. §-a (1) bekezdésének f) pontjában a,,magasabb harckészültségbe helyezéséről'' szövegrész helyébe a,,készenlétbe helyezéséről'' szövegrész lép. (5) A Hvt. 230. §-a (1) bekezdésének b) pontjában a,,harckészültségét'' szövegrész helyébe a,,készenléti állapotát'' szövegrész lép. (6) A Hvt. 36. §-a (1)–(2) bekezdésében a 8. § (1) bekezdésének d) pontjára tett hivatkozás f) pontra változik. (7) A Hvt. 73. §-ának (2), 74. §-ának (2) és 76. §-ának (2) bekezdésében a,,Honvéd Vezérkar'' szövegrész helyébe a,,honvédség'' szövegrész lép. (8) A Hszt. 237. § (1) bekezdése b) pontjának második gondolatjeles bekezdésében a,,készültségi'' szövegrész helyébe a,,készenléti'' szövegrész lép. (9) A Hkt. 31. §-ának (2) és 40. §-ának (2) bekezdésében a,,harckészültségi'' szövegrész helyébe a,,készenléti'' szövegrész, 72. §-ának (3) bekezdésében a,,harckészültség'' szövegrész helyébe a,,készenlét fokozása'' szövegrész, 53. §-ában és 71. §-ának (2) bekezdésében a,,készültségi'' szövegrész helyébe a,,készenléti'' szövegrész lép."
    }
  ],
  "definitions": []
}
