{
  "id": "hu-law-2017-61-00-00",
  "type": "statute",
  "title": "2017. évi LXI. törvény egyes törvényeknek az üzleti környezet jogi versenyképességének növelése érdekében szükséges módosításáról",
  "status": "repealed",
  "in_force_date": "2017-06-23",
  "url": "https://njt.hu/jogszabaly/2017-61-00-00",
  "description": "egyes törvényeknek az üzleti környezet jogi versenyképességének növelése érdekében szükséges módosításáról",
  "provisions": [
    {
      "provision_ref": "s1",
      "section": "1",
      "title": "1. §",
      "content": "1. §"
    },
    {
      "provision_ref": "s2",
      "section": "2",
      "title": "2. §",
      "content": "2. §"
    },
    {
      "provision_ref": "s311",
      "section": "3–11",
      "title": "3–11. §",
      "content": "3–11. §"
    },
    {
      "provision_ref": "s1218",
      "section": "12–18",
      "title": "12–18. §",
      "content": "12–18. §"
    },
    {
      "provision_ref": "s1921",
      "section": "19–21",
      "title": "19–21. §",
      "content": "19–21. §"
    },
    {
      "provision_ref": "s2227",
      "section": "22–27",
      "title": "22–27. §",
      "content": "22–27. §"
    },
    {
      "provision_ref": "s28",
      "section": "28",
      "title": "28. §",
      "content": "28. §"
    },
    {
      "provision_ref": "s2934",
      "section": "29–34",
      "title": "29–34. §",
      "content": "29–34. §"
    },
    {
      "provision_ref": "s35",
      "section": "35",
      "title": "35. §",
      "content": "35. § A Bvktv. 6. alcíme a következő 11/A. §-sal egészül ki: „11/A. § A hivatal engedélyezési eljárása esetén az ügyintézési határidő 9 hónap.”"
    },
    {
      "provision_ref": "s3638",
      "section": "36–38",
      "title": "36–38. §",
      "content": "36–38. §"
    },
    {
      "provision_ref": "s39",
      "section": "39",
      "title": "39. §",
      "content": "39. § A Bvktv. 21. §-a a következő (1a) bekezdéssel egészül ki: „(1a) A hivatal nyilvántartásba vételi eljárása esetén az ügyintézési határidő 60 nap.”"
    },
    {
      "provision_ref": "s4043",
      "section": "40–43",
      "title": "40–43. §",
      "content": "40–43. §"
    },
    {
      "provision_ref": "s44",
      "section": "44",
      "title": "44. §",
      "content": "44. § A Bvktv. a)–d) e) 13. § (2) bekezdésében és 15. § a) pontjában a „jogerőre emelkedett” szövegrész helyébe a „véglegessé vált” szöveg, f) 13. § (3) bekezdés b)–c) pontjában a „jogerőre emelkedésének” szövegrészek helyébe a „véglegessé válásának” szöveg, g) h) 18. §-ában az „a közigazgatási hatósági eljárás és szolgáltatás általános szabályairól szóló törvény (a továbbiakban: Ket.)” szövegrész helyébe az „az általános közigazgatási rendtartásról szóló törvény (a továbbiakban: Ákr.)” szöveg, i)–k) l) 30. §-ában az „a Ket.” szövegrész helyébe az „az Ákr.” szöveg, m) 31. § (1) bekezdésében az „a Ket.” szövegrész helyébe az „az Ákr.” szöveg, n) lép."
    },
    {
      "provision_ref": "s45",
      "section": "45",
      "title": "45. §",
      "content": "45. § Hatályát veszti a Bvktv. a)–f) g) 28. §-ában az „a Ket. szerinti” szöveg, h)–o)"
    },
    {
      "provision_ref": "s46",
      "section": "46",
      "title": "46. §",
      "content": "46. § (1) Ez a törvény – a (2) bekezdésben foglalt kivétellel – a kihirdetését követő 15. napon lép hatályba. (2) A 35. §, a 39. §, a 44. § e)–f) h), l)–m) pontja, és a 45. § g) pontja 2018. január 1-jén lép hatályba."
    },
    {
      "provision_ref": "s47",
      "section": "47",
      "title": "47. §",
      "content": "47. § (1) E törvény 21. §-a a 77/91/EGK, a 78/855/EGK, a 82/891/EGK tanácsi irányelvnek és a 2005/56/EK irányelvnek az egyesülések és szétválások esetében alkalmazandó jelentéstételi és dokumentációs kötelezettségek tekintetében történő módosításáról szóló, 2009. szeptember 16-i 2009/109/EK európai parlamenti és a tanácsi irányelv 4. cikk (2) bekezdésének való megfelelést szolgálja. (2) E törvény 8. alcíme a belső piaci szolgáltatásokról szóló, 2006. december 12-i 2006/123/EK európai parlamenti és tanácsi irányelvnek való megfelelést szolgálja."
    }
  ],
  "definitions": []
}
