{
  "id": "hu-law-2015-44-00-00",
  "type": "statute",
  "title": "2015. évi XLIV. törvény egyes ingatlan-nyilvántartással és földméréssel összefüggő törvények módosításáról",
  "status": "repealed",
  "in_force_date": "2015-05-02",
  "url": "https://njt.hu/jogszabaly/2015-44-00-00",
  "description": "egyes ingatlan-nyilvántartással és földméréssel összefüggő törvények módosításáról",
  "provisions": [
    {
      "provision_ref": "s12",
      "section": "1–2",
      "title": "1–2. §",
      "content": "1–2. §"
    },
    {
      "provision_ref": "s316",
      "section": "3–16",
      "title": "3–16. §",
      "content": "3–16. §"
    },
    {
      "provision_ref": "s1731",
      "section": "17–31",
      "title": "17–31. §",
      "content": "17–31. §"
    },
    {
      "provision_ref": "s3235",
      "section": "32–35",
      "title": "32–35. §",
      "content": "32–35. §"
    },
    {
      "provision_ref": "s36",
      "section": "36",
      "title": "36. §",
      "content": "36. § (1) Ez a törvény a kihirdetését követő 8. napon lép hatályba."
    }
  ],
  "definitions": []
}
