{
  "id": "hu-law-2015-53-00-00",
  "type": "statute",
  "title": "2015. évi. LIII. törvény egyes energetikai tárgyú törvények módosításáról",
  "status": "repealed",
  "in_force_date": "2015-05-09",
  "url": "https://njt.hu/jogszabaly/2015-53-00-00",
  "description": "egyes energetikai tárgyú törvények módosításáról",
  "provisions": [
    {
      "provision_ref": "s14",
      "section": "1–4",
      "title": "1–4. §",
      "content": "1–4. §"
    },
    {
      "provision_ref": "s5",
      "section": "5",
      "title": "5. §",
      "content": "5. §"
    },
    {
      "provision_ref": "s68",
      "section": "6–8",
      "title": "6–8. §",
      "content": "6–8. §"
    },
    {
      "provision_ref": "s910",
      "section": "9–10",
      "title": "9–10. §",
      "content": "9–10. §"
    },
    {
      "provision_ref": "s11",
      "section": "11",
      "title": "11. §",
      "content": "11. § Hatályát veszti az Fbkt. a) 4. § (2) bekezdésében az „, a visszapótláshoz tartozó határkeresztező kapacitásokat,” szövegrész, b) 13. § (3) bekezdésében a „, valamint a visszapótláshoz tartozó határkeresztező” szövegrész."
    },
    {
      "provision_ref": "s1224",
      "section": "12–24",
      "title": "12–24. §",
      "content": "12–24. §"
    },
    {
      "provision_ref": "s2544",
      "section": "25–44",
      "title": "25–44. §",
      "content": "25–44. §"
    },
    {
      "provision_ref": "s45",
      "section": "45",
      "title": "45. §",
      "content": "45. § A GET 133. § (1) bekezdés 3. pontja helyébe a következő rendelkezés lép: (Felhatalmazást kap a miniszter, hogy rendeletben állapítsa meg) „3. az egyetemes szolgáltatáshoz kapcsolódóan az árakat, az áralkalmazási feltételeket, az árszabályozás kereteit és a nagycsaládosokat megillető kedvezményre vonatkozó szabályokat; a felajánlás részletszabályait, a felajánlott földgázforrás árát, az igénybevételre jogosultak körét, a földgázforrás átadására vonatkozó rugalmassági szabályokat; a felajánlás keretében, a 141–141/A. §, a 141/C. §, a 141/I. § és a 141/J. § szerinti szerződések alapján értékesített földgázforrás mennyiségét és árát, valamint az ezen földgázforrásokhoz kapcsolódóan a rendszerhasználati és mobilgáz-finanszírozási költségek indokolt értékeihez képest megképződő többlet, vagy veszteség elszámolásának szabályait; a 141/A–141/C. §-ban és a 141/I–141/J. §-ban foglaltak megsértése, valamint a rendeletben meghatározott mennyiségtől való eltérés esetén alkalmazandó jogkövetkezményeket; a kapcsolt termelésszerkezet-átalakítási hozzájárulás és a kiegyenlítő hozzájárulás mértékét,”"
    },
    {
      "provision_ref": "s4649",
      "section": "46–49",
      "title": "46–49. §",
      "content": "46–49. §"
    },
    {
      "provision_ref": "s50",
      "section": "50",
      "title": "50. §",
      "content": "50. § A GET a)–l) m) 110. § (3) bekezdésében az „október” szövegrész helyébe a „május” szöveg, n)–q) lép."
    },
    {
      "provision_ref": "s51",
      "section": "51",
      "title": "51. §",
      "content": "51. § (1) (2) Hatályát veszti a GET a) 107/B. § (4) bekezdésében a „, valamint az egyetemes szolgáltatás keretében földgázt vételező felhasználók és a 141/C. § alapján felajánlott földgázt vételező felhasználók ellátásához szükséges hazai termelésű földgázmennyiséget” szövegrész, b) 107/B. § (5) bekezdése."
    },
    {
      "provision_ref": "s52",
      "section": "52",
      "title": "52. §",
      "content": "52. §"
    },
    {
      "provision_ref": "s5357",
      "section": "53–57",
      "title": "53–57. §",
      "content": "53–57. §"
    },
    {
      "provision_ref": "s58",
      "section": "58",
      "title": "58. §",
      "content": "58. § (1) Ez a törvény – a (2) bekezdésben meghatározott kivétellel – a kihirdetését követő napon lép hatályba. (2) A 11. §, a 45. §, az 50. § m) pontja és az 51. § (2) bekezdése 2015. július 1-jén lép hatályba."
    }
  ],
  "definitions": []
}
